{
    "1": {
        "customer_name": "sumit",
        "dishes": [
            {
                "dish_id": "1",
                "status": "canceled"
            }
        ]
    },
    "2": {
        "customer_name": "2",
        "dishes": [
            {
                "dish_id": "2",
                "status": "received"
            }
        ]
    },
    "3": {
        "customer_name": "1",
        "dishes": [
            {
                "dish_id": "1",
                "status": "canceled"
            }
        ]
    },
    "4": {
        "customer_name": "Sumit",
        "dishes": [
            {
                "dish_id": "3",
                "status": "received"
            }
        ]
    }
}